pyqt_loading_button/__init__.py
pyqt_loading_button/animation_type.py
pyqt_loading_button/loading_button.py
pyqt_loading_button/worker.py
pyqt_loading_button-1.0.0.dist-info/LICENSE
pyqt_loading_button-1.0.0.dist-info/METADATA
pyqt_loading_button-1.0.0.dist-info/WHEEL
pyqt_loading_button-1.0.0.dist-info/top_level.txt
pyqt_loading_button-1.0.0.dist-info/RECORD
