Metadata-Version: 2.1
Name: pyqt-loading-button
Version: 1.0.0
Summary: A QPushButton with built-in loading animations for PyQt and PySide
Home-page: https://github.com/marcohenning/pyqt-loading-button
Author: Marco Henning
License: MIT
Keywords: python,pyqt,qt,button,animation
Classifier: Programming Language :: Python :: 3
Classifier: Operating System :: OS Independent
Classifier: License :: OSI Approved :: MIT License
Requires-Python: >=3.7
License-File: LICENSE
Requires-Dist: QtPy>=2.4.1
